CLAchievements-0.1.0.dist-info/DESCRIPTION.rst
CLAchievements-0.1.0.dist-info/METADATA
CLAchievements-0.1.0.dist-info/RECORD
CLAchievements-0.1.0.dist-info/WHEEL
CLAchievements-0.1.0.dist-info/entry_points.txt
CLAchievements-0.1.0.dist-info/metadata.json
CLAchievements-0.1.0.dist-info/top_level.txt
clachievements/__init__.py
clachievements/__main__.py
clachievements/db.py
clachievements/notify.py
clachievements/testutils.py
clachievements/achievements/__init__.py
clachievements/achievements/count.py
clachievements/achievements/fs.py
clachievements/achievements/ls.py
clachievements/achievements/meta.py
clachievements/achievements/options.py
clachievements/alias/__init__.py
clachievements/alias/__main__.py
clachievements/data/icons/.gitignore
clachievements/data/icons/Makefile
clachievements/data/icons/copyleft.svg
clachievements/data/icons/copyleft.svg.md
clachievements/data/icons/star.svg
clachievements/data/icons/star.tex
clachievements/report/__init__.py
clachievements/report/__main__.py
clachievements/reset/__init__.py
clachievements/reset/__main__.py
clachievements/run/__init__.py
clachievements/run/__main__.py
