Metadata-Version: 2.0
Name: CLAchievements
Version: 0.1.0
Summary: Command Line Achievements — Make command line fun again!
Home-page: http://git.framasoft.org/spalax/clachievements
Author: Louis Paternault
Author-email: spalax@gresille.org
License: GPLv3 or any later version
Platform: UNKNOWN
Classifier: Development Status :: 4 - Beta
Classifier: Environment :: Console
Classifier: Intended Audience :: System Administrators
Classifier: License :: OSI Approved :: GNU General Public License v3 or later (GPLv3+)
Classifier: Programming Language :: Python :: 3
Classifier: Programming Language :: Python :: 3 :: Only
Classifier: Topic :: Games/Entertainment
Classifier: Topic :: System :: Shells
Requires-Dist: argdispatch
Requires-Dist: multidict
Requires-Dist: pyxdg
Requires-Dist: straight.plugin
Provides-Extra: pgi
Requires-Dist: pgi; extra == 'pgi'
